package com.avrgaming.civcraft.threading.timers;

public class PlayerProximityComponentTimer
  implements Runnable
{
  /* Error */
  public void run()
  {
    // Byte code:
    //   0: getstatic 17	com/avrgaming/civcraft/components/Component:componentsLock	Ljava/util/concurrent/locks/ReentrantLock;
    //   3: invokevirtual 23	java/util/concurrent/locks/ReentrantLock:lock	()V
    //   6: getstatic 28	com/avrgaming/civcraft/components/Component:componentsByType	Ljava/util/concurrent/ConcurrentHashMap;
    //   9: ldc 32
    //   11: invokevirtual 34	java/lang/Class:getName	()Ljava/lang/String;
    //   14: invokevirtual 40	java/util/concurrent/ConcurrentHashMap:get	(Ljava/lang/Object;)Ljava/lang/Object;
    //   17: checkcast 46	java/util/ArrayList
    //   20: astore_1
    //   21: aload_1
    //   22: ifnonnull +10 -> 32
    //   25: getstatic 17	com/avrgaming/civcraft/components/Component:componentsLock	Ljava/util/concurrent/locks/ReentrantLock;
    //   28: invokevirtual 48	java/util/concurrent/locks/ReentrantLock:unlock	()V
    //   31: return
    //   32: aload_1
    //   33: invokevirtual 51	java/util/ArrayList:iterator	()Ljava/util/Iterator;
    //   36: astore_3
    //   37: goto +69 -> 106
    //   40: aload_3
    //   41: invokeinterface 55 1 0
    //   46: checkcast 18	com/avrgaming/civcraft/components/Component
    //   49: astore_2
    //   50: aload_2
    //   51: instanceof 32
    //   54: ifeq +52 -> 106
    //   57: aload_2
    //   58: checkcast 32	com/avrgaming/civcraft/components/PlayerProximityComponent
    //   61: astore 4
    //   63: aload 4
    //   65: getfield 61	com/avrgaming/civcraft/components/PlayerProximityComponent:lock	Ljava/util/concurrent/locks/ReentrantLock;
    //   68: invokevirtual 63	java/util/concurrent/locks/ReentrantLock:tryLock	()Z
    //   71: ifeq +35 -> 106
    //   74: aload 4
    //   76: invokestatic 67	com/avrgaming/civcraft/cache/PlayerLocationCache:getCache	()Ljava/util/Collection;
    //   79: invokevirtual 73	com/avrgaming/civcraft/components/PlayerProximityComponent:buildNearbyPlayers	(Ljava/util/Collection;)V
    //   82: goto +16 -> 98
    //   85: astore 5
    //   87: aload 4
    //   89: getfield 61	com/avrgaming/civcraft/components/PlayerProximityComponent:lock	Ljava/util/concurrent/locks/ReentrantLock;
    //   92: invokevirtual 48	java/util/concurrent/locks/ReentrantLock:unlock	()V
    //   95: aload 5
    //   97: athrow
    //   98: aload 4
    //   100: getfield 61	com/avrgaming/civcraft/components/PlayerProximityComponent:lock	Ljava/util/concurrent/locks/ReentrantLock;
    //   103: invokevirtual 48	java/util/concurrent/locks/ReentrantLock:unlock	()V
    //   106: aload_3
    //   107: invokeinterface 77 1 0
    //   112: ifne -72 -> 40
    //   115: goto +14 -> 129
    //   118: astore 6
    //   120: getstatic 17	com/avrgaming/civcraft/components/Component:componentsLock	Ljava/util/concurrent/locks/ReentrantLock;
    //   123: invokevirtual 48	java/util/concurrent/locks/ReentrantLock:unlock	()V
    //   126: aload 6
    //   128: athrow
    //   129: getstatic 17	com/avrgaming/civcraft/components/Component:componentsLock	Ljava/util/concurrent/locks/ReentrantLock;
    //   132: invokevirtual 48	java/util/concurrent/locks/ReentrantLock:unlock	()V
    //   135: return
    // Line number table:
    //   Java source line #38	-> byte code offset #0
    //   Java source line #40	-> byte code offset #6
    //   Java source line #42	-> byte code offset #21
    //   Java source line #63	-> byte code offset #25
    //   Java source line #43	-> byte code offset #31
    //   Java source line #49	-> byte code offset #32
    //   Java source line #50	-> byte code offset #50
    //   Java source line #51	-> byte code offset #57
    //   Java source line #53	-> byte code offset #63
    //   Java source line #55	-> byte code offset #74
    //   Java source line #56	-> byte code offset #82
    //   Java source line #57	-> byte code offset #87
    //   Java source line #58	-> byte code offset #95
    //   Java source line #57	-> byte code offset #98
    //   Java source line #49	-> byte code offset #106
    //   Java source line #62	-> byte code offset #115
    //   Java source line #63	-> byte code offset #120
    //   Java source line #64	-> byte code offset #126
    //   Java source line #63	-> byte code offset #129
    //   Java source line #65	-> byte code offset #135
    // Local variable table:
    //   start	length	slot	name	signature
    //   0	136	0	this	PlayerProximityComponentTimer
    //   20	13	1	proximityComponents	java.util.ArrayList<com.avrgaming.civcraft.components.Component>
    //   49	9	2	comp	com.avrgaming.civcraft.components.Component
    //   36	71	3	localIterator	java.util.Iterator
    //   61	38	4	ppc	com.avrgaming.civcraft.components.PlayerProximityComponent
    //   85	11	5	localObject1	Object
    //   118	9	6	localObject2	Object
    // Exception table:
    //   from	to	target	type
    //   74	85	85	finally
    //   6	25	118	finally
    //   32	118	118	finally
  }
}


/* Location:              C:\Users\Adrian\Desktop\CivCraft1.1.jar!\com\avrgaming\civcraft\threading\timers\PlayerProximityComponentTimer.class
 * Java compiler version: 7 (51.0)
 * JD-Core Version:       0.7.1
 */