/*    */ package com.avrgaming.civcraft.threading.timers;
/*    */ 
/*    */ import com.avrgaming.civcraft.threading.CivAsyncTask;
/*    */ import java.util.concurrent.locks.ReentrantLock;
/*    */ 
/*    */ 
/*    */ 
/*    */ 
/*    */ 
/*    */ 
/*    */ 
/*    */ 
/*    */ 
/*    */ 
/*    */ 
/*    */ 
/*    */ 
/*    */ 
/*    */ 
/*    */ 
/*    */ 
/*    */ 
/*    */ 
/*    */ 
/*    */ 
/*    */ 
/*    */ 
/*    */ 
/*    */ 
/*    */ 
/*    */ 
/*    */ 
/*    */ 
/*    */ public class UpdateEventTimer
/*    */   extends CivAsyncTask
/*    */ {
/* 37 */   public static ReentrantLock lock = new ReentrantLock();
/*    */   
/*    */   /* Error */
/*    */   public void run()
/*    */   {
/*    */     // Byte code:
/*    */     //   0: getstatic 15	com/avrgaming/civcraft/threading/timers/UpdateEventTimer:lock	Ljava/util/concurrent/locks/ReentrantLock;
/*    */     //   3: invokevirtual 23	java/util/concurrent/locks/ReentrantLock:tryLock	()Z
/*    */     //   6: ifne +4 -> 10
/*    */     //   9: return
/*    */     //   10: invokestatic 27	com/avrgaming/civcraft/main/CivGlobal:getStructureIterator	()Ljava/util/Iterator;
/*    */     //   13: astore_1
/*    */     //   14: goto +117 -> 131
/*    */     //   17: aload_1
/*    */     //   18: invokeinterface 33 1 0
/*    */     //   23: checkcast 39	java/util/Map$Entry
/*    */     //   26: invokeinterface 41 1 0
/*    */     //   31: checkcast 44	com/avrgaming/civcraft/structure/Structure
/*    */     //   34: astore_2
/*    */     //   35: aload_2
/*    */     //   36: invokevirtual 46	com/avrgaming/civcraft/structure/Structure:isActive	()Z
/*    */     //   39: ifne +6 -> 45
/*    */     //   42: goto +89 -> 131
/*    */     //   45: aload_2
/*    */     //   46: invokevirtual 49	com/avrgaming/civcraft/structure/Structure:getUpdateEvent	()Ljava/lang/String;
/*    */     //   49: ifnull +70 -> 119
/*    */     //   52: aload_2
/*    */     //   53: invokevirtual 49	com/avrgaming/civcraft/structure/Structure:getUpdateEvent	()Ljava/lang/String;
/*    */     //   56: ldc 53
/*    */     //   58: invokevirtual 55	java/lang/String:equals	(Ljava/lang/Object;)Z
/*    */     //   61: ifne +58 -> 119
/*    */     //   64: aload_2
/*    */     //   65: invokevirtual 49	com/avrgaming/civcraft/structure/Structure:getUpdateEvent	()Ljava/lang/String;
/*    */     //   68: ldc 61
/*    */     //   70: invokevirtual 55	java/lang/String:equals	(Ljava/lang/Object;)Z
/*    */     //   73: ifeq +46 -> 119
/*    */     //   76: getstatic 63	com/avrgaming/civcraft/main/CivGlobal:trommelsEnabled	Z
/*    */     //   79: ifne +6 -> 85
/*    */     //   82: goto +49 -> 131
/*    */     //   85: new 67	java/lang/StringBuilder
/*    */     //   88: dup
/*    */     //   89: ldc 69
/*    */     //   91: invokespecial 71	java/lang/StringBuilder:<init>	(Ljava/lang/String;)V
/*    */     //   94: aload_2
/*    */     //   95: invokevirtual 74	com/avrgaming/civcraft/structure/Structure:getCorner	()Lcom/avrgaming/civcraft/util/BlockCoord;
/*    */     //   98: invokevirtual 78	com/avrgaming/civcraft/util/BlockCoord:toString	()Ljava/lang/String;
/*    */     //   101: invokevirtual 83	java/lang/StringBuilder:append	(Ljava/lang/String;)Ljava/lang/StringBuilder;
/*    */     //   104: invokevirtual 87	java/lang/StringBuilder:toString	()Ljava/lang/String;
/*    */     //   107: new 88	com/avrgaming/civcraft/threading/tasks/TrommelAsyncTask
/*    */     //   110: dup
/*    */     //   111: aload_2
/*    */     //   112: invokespecial 90	com/avrgaming/civcraft/threading/tasks/TrommelAsyncTask:<init>	(Lcom/avrgaming/civcraft/structure/Structure;)V
/*    */     //   115: lconst_0
/*    */     //   116: invokestatic 93	com/avrgaming/civcraft/threading/TaskMaster:asyncTask	(Ljava/lang/String;Ljava/lang/Runnable;J)V
/*    */     //   119: aload_2
/*    */     //   120: invokevirtual 99	com/avrgaming/civcraft/structure/Structure:onUpdate	()V
/*    */     //   123: goto +8 -> 131
/*    */     //   126: astore_3
/*    */     //   127: aload_3
/*    */     //   128: invokevirtual 102	java/lang/Exception:printStackTrace	()V
/*    */     //   131: aload_1
/*    */     //   132: invokeinterface 107 1 0
/*    */     //   137: ifne -120 -> 17
/*    */     //   140: invokestatic 110	com/avrgaming/civcraft/main/CivGlobal:getWonders	()Ljava/util/Collection;
/*    */     //   143: invokeinterface 114 1 0
/*    */     //   148: astore_3
/*    */     //   149: goto +17 -> 166
/*    */     //   152: aload_3
/*    */     //   153: invokeinterface 33 1 0
/*    */     //   158: checkcast 119	com/avrgaming/civcraft/structure/wonders/Wonder
/*    */     //   161: astore_2
/*    */     //   162: aload_2
/*    */     //   163: invokevirtual 121	com/avrgaming/civcraft/structure/wonders/Wonder:onUpdate	()V
/*    */     //   166: aload_3
/*    */     //   167: invokeinterface 107 1 0
/*    */     //   172: ifne -20 -> 152
/*    */     //   175: invokestatic 122	com/avrgaming/civcraft/main/CivGlobal:getCamps	()Ljava/util/Collection;
/*    */     //   178: invokeinterface 114 1 0
/*    */     //   183: astore_3
/*    */     //   184: goto +35 -> 219
/*    */     //   187: aload_3
/*    */     //   188: invokeinterface 33 1 0
/*    */     //   193: checkcast 125	com/avrgaming/civcraft/camp/Camp
/*    */     //   196: astore_2
/*    */     //   197: aload_2
/*    */     //   198: getfield 127	com/avrgaming/civcraft/camp/Camp:sifterLock	Ljava/util/concurrent/locks/ReentrantLock;
/*    */     //   201: invokevirtual 130	java/util/concurrent/locks/ReentrantLock:isLocked	()Z
/*    */     //   204: ifne +15 -> 219
/*    */     //   207: new 133	com/avrgaming/civcraft/camp/CampUpdateTick
/*    */     //   210: dup
/*    */     //   211: aload_2
/*    */     //   212: invokespecial 135	com/avrgaming/civcraft/camp/CampUpdateTick:<init>	(Lcom/avrgaming/civcraft/camp/Camp;)V
/*    */     //   215: lconst_0
/*    */     //   216: invokestatic 138	com/avrgaming/civcraft/threading/TaskMaster:asyncTask	(Ljava/lang/Runnable;J)V
/*    */     //   219: aload_3
/*    */     //   220: invokeinterface 107 1 0
/*    */     //   225: ifne -38 -> 187
/*    */     //   228: goto +14 -> 242
/*    */     //   231: astore 4
/*    */     //   233: getstatic 15	com/avrgaming/civcraft/threading/timers/UpdateEventTimer:lock	Ljava/util/concurrent/locks/ReentrantLock;
/*    */     //   236: invokevirtual 141	java/util/concurrent/locks/ReentrantLock:unlock	()V
/*    */     //   239: aload 4
/*    */     //   241: athrow
/*    */     //   242: getstatic 15	com/avrgaming/civcraft/threading/timers/UpdateEventTimer:lock	Ljava/util/concurrent/locks/ReentrantLock;
/*    */     //   245: invokevirtual 141	java/util/concurrent/locks/ReentrantLock:unlock	()V
/*    */     //   248: return
/*    */     // Line number table:
/*    */     //   Java source line #45	-> byte code offset #0
/*    */     //   Java source line #46	-> byte code offset #9
/*    */     //   Java source line #51	-> byte code offset #10
/*    */     //   Java source line #53	-> byte code offset #14
/*    */     //   Java source line #54	-> byte code offset #17
/*    */     //   Java source line #56	-> byte code offset #35
/*    */     //   Java source line #57	-> byte code offset #42
/*    */     //   Java source line #60	-> byte code offset #45
/*    */     //   Java source line #61	-> byte code offset #64
/*    */     //   Java source line #62	-> byte code offset #76
/*    */     //   Java source line #63	-> byte code offset #82
/*    */     //   Java source line #66	-> byte code offset #85
/*    */     //   Java source line #70	-> byte code offset #119
/*    */     //   Java source line #71	-> byte code offset #123
/*    */     //   Java source line #72	-> byte code offset #127
/*    */     //   Java source line #53	-> byte code offset #131
/*    */     //   Java source line #84	-> byte code offset #140
/*    */     //   Java source line #85	-> byte code offset #162
/*    */     //   Java source line #84	-> byte code offset #166
/*    */     //   Java source line #89	-> byte code offset #175
/*    */     //   Java source line #90	-> byte code offset #197
/*    */     //   Java source line #91	-> byte code offset #207
/*    */     //   Java source line #89	-> byte code offset #219
/*    */     //   Java source line #95	-> byte code offset #228
/*    */     //   Java source line #96	-> byte code offset #233
/*    */     //   Java source line #97	-> byte code offset #239
/*    */     //   Java source line #96	-> byte code offset #242
/*    */     //   Java source line #99	-> byte code offset #248
/*    */     // Local variable table:
/*    */     //   start	length	slot	name	signature
/*    */     //   0	249	0	this	UpdateEventTimer
/*    */     //   13	119	1	iter	java.util.Iterator<java.util.Map.Entry<com.avrgaming.civcraft.util.BlockCoord, com.avrgaming.civcraft.structure.Structure>>
/*    */     //   34	86	2	struct	com.avrgaming.civcraft.structure.Structure
/*    */     //   161	2	2	wonder	com.avrgaming.civcraft.structure.wonders.Wonder
/*    */     //   196	16	2	camp	com.avrgaming.civcraft.camp.Camp
/*    */     //   126	94	3	e	Exception
/*    */     //   231	9	4	localObject	Object
/*    */     // Exception table:
/*    */     //   from	to	target	type
/*    */     //   45	82	126	java/lang/Exception
/*    */     //   85	123	126	java/lang/Exception
/*    */     //   10	231	231	finally
/*    */   }
/*    */ }


/* Location:              C:\Users\Adrian\Desktop\CivCraft1.1.jar!\com\avrgaming\civcraft\threading\timers\UpdateEventTimer.class
 * Java compiler version: 7 (51.0)
 * JD-Core Version:       0.7.1
 */