/*    */ package com.avrgaming.civcraft.structure.farm;
/*    */ 
/*    */ import com.avrgaming.civcraft.threading.CivAsyncTask;
/*    */ import java.util.Queue;
/*    */ 
/*    */ 
/*    */ 
/*    */ 
/*    */ 
/*    */ 
/*    */ 
/*    */ 
/*    */ 
/*    */ 
/*    */ 
/*    */ 
/*    */ 
/*    */ 
/*    */ 
/*    */ 
/*    */ 
/*    */ 
/*    */ 
/*    */ 
/*    */ 
/*    */ 
/*    */ public class FarmGrowthRegrowTask
/*    */   extends CivAsyncTask
/*    */ {
/*    */   Queue<FarmChunk> farmsToGrow;
/*    */   
/*    */   public FarmGrowthRegrowTask(Queue<FarmChunk> farms)
/*    */   {
/* 34 */     this.farmsToGrow = farms;
/*    */   }
/*    */   
/*    */   /* Error */
/*    */   public void run()
/*    */   {
/*    */     // Byte code:
/*    */     //   0: new 25	java/util/LinkedList
/*    */     //   3: dup
/*    */     //   4: invokespecial 27	java/util/LinkedList:<init>	()V
/*    */     //   7: astore_1
/*    */     //   8: new 28	java/lang/StringBuilder
/*    */     //   11: dup
/*    */     //   12: ldc 30
/*    */     //   14: invokespecial 32	java/lang/StringBuilder:<init>	(Ljava/lang/String;)V
/*    */     //   17: aload_0
/*    */     //   18: getfield 16	com/avrgaming/civcraft/structure/farm/FarmGrowthRegrowTask:farmsToGrow	Ljava/util/Queue;
/*    */     //   21: invokeinterface 35 1 0
/*    */     //   26: invokevirtual 41	java/lang/StringBuilder:append	(I)Ljava/lang/StringBuilder;
/*    */     //   29: ldc 45
/*    */     //   31: invokevirtual 47	java/lang/StringBuilder:append	(Ljava/lang/String;)Ljava/lang/StringBuilder;
/*    */     //   34: invokevirtual 50	java/lang/StringBuilder:toString	()Ljava/lang/String;
/*    */     //   37: invokestatic 54	com/avrgaming/civcraft/main/CivLog:info	(Ljava/lang/String;)V
/*    */     //   40: goto +64 -> 104
/*    */     //   43: aload_2
/*    */     //   44: getfield 59	com/avrgaming/civcraft/structure/farm/FarmChunk:lock	Ljava/util/concurrent/locks/ReentrantLock;
/*    */     //   47: invokevirtual 65	java/util/concurrent/locks/ReentrantLock:tryLock	()Z
/*    */     //   50: ifeq +46 -> 96
/*    */     //   53: aload_2
/*    */     //   54: aload_0
/*    */     //   55: invokevirtual 71	com/avrgaming/civcraft/structure/farm/FarmChunk:processGrowth	(Lcom/avrgaming/civcraft/threading/CivAsyncTask;)V
/*    */     //   58: goto +28 -> 86
/*    */     //   61: astore_3
/*    */     //   62: aload_3
/*    */     //   63: invokevirtual 75	java/lang/InterruptedException:printStackTrace	()V
/*    */     //   66: aload_2
/*    */     //   67: getfield 59	com/avrgaming/civcraft/structure/farm/FarmChunk:lock	Ljava/util/concurrent/locks/ReentrantLock;
/*    */     //   70: invokevirtual 80	java/util/concurrent/locks/ReentrantLock:unlock	()V
/*    */     //   73: return
/*    */     //   74: astore 4
/*    */     //   76: aload_2
/*    */     //   77: getfield 59	com/avrgaming/civcraft/structure/farm/FarmChunk:lock	Ljava/util/concurrent/locks/ReentrantLock;
/*    */     //   80: invokevirtual 80	java/util/concurrent/locks/ReentrantLock:unlock	()V
/*    */     //   83: aload 4
/*    */     //   85: athrow
/*    */     //   86: aload_2
/*    */     //   87: getfield 59	com/avrgaming/civcraft/structure/farm/FarmChunk:lock	Ljava/util/concurrent/locks/ReentrantLock;
/*    */     //   90: invokevirtual 80	java/util/concurrent/locks/ReentrantLock:unlock	()V
/*    */     //   93: goto +11 -> 104
/*    */     //   96: aload_1
/*    */     //   97: aload_2
/*    */     //   98: invokeinterface 83 2 0
/*    */     //   103: pop
/*    */     //   104: aload_0
/*    */     //   105: getfield 16	com/avrgaming/civcraft/structure/farm/FarmGrowthRegrowTask:farmsToGrow	Ljava/util/Queue;
/*    */     //   108: invokeinterface 87 1 0
/*    */     //   113: checkcast 60	com/avrgaming/civcraft/structure/farm/FarmChunk
/*    */     //   116: dup
/*    */     //   117: astore_2
/*    */     //   118: ifnonnull -75 -> 43
/*    */     //   121: aload_1
/*    */     //   122: invokeinterface 35 1 0
/*    */     //   127: ifle +14 -> 141
/*    */     //   130: new 1	com/avrgaming/civcraft/structure/farm/FarmGrowthRegrowTask
/*    */     //   133: dup
/*    */     //   134: aload_1
/*    */     //   135: invokespecial 91	com/avrgaming/civcraft/structure/farm/FarmGrowthRegrowTask:<init>	(Ljava/util/Queue;)V
/*    */     //   138: invokestatic 93	com/avrgaming/civcraft/threading/TaskMaster:syncTask	(Ljava/lang/Runnable;)V
/*    */     //   141: return
/*    */     // Line number table:
/*    */     //   Java source line #40	-> byte code offset #0
/*    */     //   Java source line #41	-> byte code offset #8
/*    */     //   Java source line #44	-> byte code offset #40
/*    */     //   Java source line #45	-> byte code offset #43
/*    */     //   Java source line #48	-> byte code offset #53
/*    */     //   Java source line #49	-> byte code offset #58
/*    */     //   Java source line #50	-> byte code offset #62
/*    */     //   Java source line #54	-> byte code offset #66
/*    */     //   Java source line #51	-> byte code offset #73
/*    */     //   Java source line #53	-> byte code offset #74
/*    */     //   Java source line #54	-> byte code offset #76
/*    */     //   Java source line #55	-> byte code offset #83
/*    */     //   Java source line #54	-> byte code offset #86
/*    */     //   Java source line #56	-> byte code offset #93
/*    */     //   Java source line #57	-> byte code offset #96
/*    */     //   Java source line #44	-> byte code offset #104
/*    */     //   Java source line #61	-> byte code offset #121
/*    */     //   Java source line #62	-> byte code offset #130
/*    */     //   Java source line #64	-> byte code offset #141
/*    */     // Local variable table:
/*    */     //   start	length	slot	name	signature
/*    */     //   0	142	0	this	FarmGrowthRegrowTask
/*    */     //   7	128	1	regrow	Queue<FarmChunk>
/*    */     //   43	55	2	fc	FarmChunk
/*    */     //   117	2	2	fc	FarmChunk
/*    */     //   61	2	3	e	InterruptedException
/*    */     //   74	10	4	localObject	Object
/*    */     // Exception table:
/*    */     //   from	to	target	type
/*    */     //   53	58	61	java/lang/InterruptedException
/*    */     //   53	66	74	finally
/*    */   }
/*    */ }


/* Location:              C:\Users\Adrian\Desktop\CivCraft1.1.jar!\com\avrgaming\civcraft\structure\farm\FarmGrowthRegrowTask.class
 * Java compiler version: 7 (51.0)
 * JD-Core Version:       0.7.1
 */