/*    */ package com.avrgaming.civcraft.structure.farm;
/*    */ 
/*    */ import com.avrgaming.civcraft.threading.CivAsyncTask;
/*    */ 
/*    */ public class FarmGrowthSyncTask
/*    */   extends CivAsyncTask
/*    */ {
/*    */   /* Error */
/*    */   public void processFarmChunks()
/*    */   {
/*    */     // Byte code:
/*    */     //   0: getstatic 15	com/avrgaming/civcraft/main/CivGlobal:growthEnabled	Z
/*    */     //   3: ifne +4 -> 7
/*    */     //   6: return
/*    */     //   7: invokestatic 21	com/avrgaming/civcraft/main/CivGlobal:getFarmChunks	()Ljava/util/Collection;
/*    */     //   10: invokeinterface 25 1 0
/*    */     //   15: astore_2
/*    */     //   16: goto +101 -> 117
/*    */     //   19: aload_2
/*    */     //   20: invokeinterface 31 1 0
/*    */     //   25: checkcast 37	com/avrgaming/civcraft/structure/farm/FarmChunk
/*    */     //   28: astore_1
/*    */     //   29: aload_1
/*    */     //   30: invokevirtual 39	com/avrgaming/civcraft/structure/farm/FarmChunk:getTown	()Lcom/avrgaming/civcraft/object/Town;
/*    */     //   33: ifnull +10 -> 43
/*    */     //   36: aload_1
/*    */     //   37: invokevirtual 43	com/avrgaming/civcraft/structure/farm/FarmChunk:getStruct	()Lcom/avrgaming/civcraft/structure/Structure;
/*    */     //   40: ifnonnull +14 -> 54
/*    */     //   43: getstatic 47	java/lang/System:out	Ljava/io/PrintStream;
/*    */     //   46: ldc 53
/*    */     //   48: invokevirtual 55	java/io/PrintStream:println	(Ljava/lang/String;)V
/*    */     //   51: goto +66 -> 117
/*    */     //   54: aload_1
/*    */     //   55: getfield 61	com/avrgaming/civcraft/structure/farm/FarmChunk:lock	Ljava/util/concurrent/locks/ReentrantLock;
/*    */     //   58: ldc2_w 65
/*    */     //   61: getstatic 67	java/util/concurrent/TimeUnit:MILLISECONDS	Ljava/util/concurrent/TimeUnit;
/*    */     //   64: invokevirtual 73	java/util/concurrent/locks/ReentrantLock:tryLock	(JLjava/util/concurrent/TimeUnit;)Z
/*    */     //   67: ifne +10 -> 77
/*    */     //   70: return
/*    */     //   71: astore_3
/*    */     //   72: aload_3
/*    */     //   73: invokevirtual 79	java/lang/InterruptedException:printStackTrace	()V
/*    */     //   76: return
/*    */     //   77: aload_1
/*    */     //   78: aload_0
/*    */     //   79: invokevirtual 84	com/avrgaming/civcraft/structure/farm/FarmChunk:processGrowth	(Lcom/avrgaming/civcraft/threading/CivAsyncTask;)V
/*    */     //   82: goto +28 -> 110
/*    */     //   85: astore_3
/*    */     //   86: aload_3
/*    */     //   87: invokevirtual 79	java/lang/InterruptedException:printStackTrace	()V
/*    */     //   90: aload_1
/*    */     //   91: getfield 61	com/avrgaming/civcraft/structure/farm/FarmChunk:lock	Ljava/util/concurrent/locks/ReentrantLock;
/*    */     //   94: invokevirtual 88	java/util/concurrent/locks/ReentrantLock:unlock	()V
/*    */     //   97: return
/*    */     //   98: astore 4
/*    */     //   100: aload_1
/*    */     //   101: getfield 61	com/avrgaming/civcraft/structure/farm/FarmChunk:lock	Ljava/util/concurrent/locks/ReentrantLock;
/*    */     //   104: invokevirtual 88	java/util/concurrent/locks/ReentrantLock:unlock	()V
/*    */     //   107: aload 4
/*    */     //   109: athrow
/*    */     //   110: aload_1
/*    */     //   111: getfield 61	com/avrgaming/civcraft/structure/farm/FarmChunk:lock	Ljava/util/concurrent/locks/ReentrantLock;
/*    */     //   114: invokevirtual 88	java/util/concurrent/locks/ReentrantLock:unlock	()V
/*    */     //   117: aload_2
/*    */     //   118: invokeinterface 91 1 0
/*    */     //   123: ifne -104 -> 19
/*    */     //   126: return
/*    */     // Line number table:
/*    */     //   Java source line #30	-> byte code offset #0
/*    */     //   Java source line #31	-> byte code offset #6
/*    */     //   Java source line #35	-> byte code offset #7
/*    */     //   Java source line #36	-> byte code offset #29
/*    */     //   Java source line #37	-> byte code offset #43
/*    */     //   Java source line #38	-> byte code offset #51
/*    */     //   Java source line #43	-> byte code offset #54
/*    */     //   Java source line #44	-> byte code offset #70
/*    */     //   Java source line #46	-> byte code offset #71
/*    */     //   Java source line #47	-> byte code offset #72
/*    */     //   Java source line #48	-> byte code offset #76
/*    */     //   Java source line #52	-> byte code offset #77
/*    */     //   Java source line #53	-> byte code offset #82
/*    */     //   Java source line #54	-> byte code offset #86
/*    */     //   Java source line #58	-> byte code offset #90
/*    */     //   Java source line #55	-> byte code offset #97
/*    */     //   Java source line #57	-> byte code offset #98
/*    */     //   Java source line #58	-> byte code offset #100
/*    */     //   Java source line #59	-> byte code offset #107
/*    */     //   Java source line #58	-> byte code offset #110
/*    */     //   Java source line #35	-> byte code offset #117
/*    */     //   Java source line #68	-> byte code offset #126
/*    */     // Local variable table:
/*    */     //   start	length	slot	name	signature
/*    */     //   0	127	0	this	FarmGrowthSyncTask
/*    */     //   28	83	1	fc	FarmChunk
/*    */     //   15	103	2	localIterator	java.util.Iterator
/*    */     //   71	2	3	e1	InterruptedException
/*    */     //   85	2	3	e	InterruptedException
/*    */     //   98	10	4	localObject	Object
/*    */     // Exception table:
/*    */     //   from	to	target	type
/*    */     //   54	70	71	java/lang/InterruptedException
/*    */     //   77	82	85	java/lang/InterruptedException
/*    */     //   77	90	98	finally
/*    */   }
/*    */   
/*    */   public void run()
/*    */   {
/*    */     try
/*    */     {
/* 74 */       processFarmChunks();
/*    */     } catch (Exception e) {
/* 76 */       e.printStackTrace();
/*    */     }
/*    */   }
/*    */ }


/* Location:              C:\Users\Adrian\Desktop\CivCraft1.1.jar!\com\avrgaming\civcraft\structure\farm\FarmGrowthSyncTask.class
 * Java compiler version: 7 (51.0)
 * JD-Core Version:       0.7.1
 */